dify_oapi/__init__.py
dify_oapi/api/__init__.py
dify_oapi/api/chat/__init__.py
dify_oapi/api/chat/service.py
dify_oapi/api/chat/v1/__init__.py
dify_oapi/api/chat/v1/model/__init__.py
dify_oapi/api/chat/v1/model/agent_thought.py
dify_oapi/api/chat/v1/model/annotation_info.py
dify_oapi/api/chat/v1/model/app_info.py
dify_oapi/api/chat/v1/model/app_parameters.py
dify_oapi/api/chat/v1/model/chat_file.py
dify_oapi/api/chat/v1/model/chat_request.py
dify_oapi/api/chat/v1/model/chat_request_body.py
dify_oapi/api/chat/v1/model/chat_response.py
dify_oapi/api/chat/v1/model/chat_types.py
dify_oapi/api/chat/v1/model/configure_annotation_reply_request.py
dify_oapi/api/chat/v1/model/configure_annotation_reply_request_body.py
dify_oapi/api/chat/v1/model/configure_annotation_reply_response.py
dify_oapi/api/chat/v1/model/conversation_info.py
dify_oapi/api/chat/v1/model/conversation_variable.py
dify_oapi/api/chat/v1/model/create_annotation_request.py
dify_oapi/api/chat/v1/model/create_annotation_request_body.py
dify_oapi/api/chat/v1/model/create_annotation_response.py
dify_oapi/api/chat/v1/model/delete_annotation_request.py
dify_oapi/api/chat/v1/model/delete_annotation_response.py
dify_oapi/api/chat/v1/model/delete_conversation_request.py
dify_oapi/api/chat/v1/model/delete_conversation_request_body.py
dify_oapi/api/chat/v1/model/delete_conversation_response.py
dify_oapi/api/chat/v1/model/feedback_info.py
dify_oapi/api/chat/v1/model/file_info.py
dify_oapi/api/chat/v1/model/get_annotation_reply_status_request.py
dify_oapi/api/chat/v1/model/get_annotation_reply_status_response.py
dify_oapi/api/chat/v1/model/get_conversation_list_request.py
dify_oapi/api/chat/v1/model/get_conversation_list_response.py
dify_oapi/api/chat/v1/model/get_conversation_variables_request.py
dify_oapi/api/chat/v1/model/get_conversation_variables_response.py
dify_oapi/api/chat/v1/model/get_conversations_request.py
dify_oapi/api/chat/v1/model/get_suggested_questions_request.py
dify_oapi2-1.1.2.dist-info/METADATA
dify_oapi2-1.1.2.dist-info/WHEEL
dify_oapi2-1.1.2.dist-info/licenses/LICENSE
dify_oapi2-1.1.2.dist-info/RECORD
