Metadata-Version: 2.4
Name: dify-oapi2
Version: 1.1.2
Summary: A package for interacting with the Dify Service-API
License: MIT
License-File: LICENSE
Keywords: dify,nlp,ai,language-processing
Author: Oscaner Miao
Author-email: oscaner1997@gmail.com
Requires-Python: >=3.10
Classifier: License :: OSI Approved :: MIT License
Classifier: Programming Language :: Python :: 3
Classifier: Programming Language :: Python :: 3.10
Classifier: Programming Language :: Python :: 3.11
Classifier: Programming Language :: Python :: 3.12
Classifier: Programming Language :: Python :: 3.13
Classifier: Programming Language :: Python :: 3.14
Requires-Dist: httpx (>=0,<1)
Requires-Dist: pydantic (>=2,<3)
Project-URL: Homepage, https://github.com/nodite/dify-oapi2
Project-URL: Source, https://github.com/nodite/dify-oapi2
